skytek_arcgis_integration/VERSION
skytek_arcgis_integration/__init__.py
skytek_arcgis_integration/client.py
skytek_arcgis_integration/serializers.py
skytek_arcgis_integration/urls.py
skytek_arcgis_integration/utils.py
skytek_arcgis_integration/views.py
skytek_arcgis_integration/generator/__init__.py
skytek_arcgis_integration/generator/feature_layer_generator.py
skytek_arcgis_integration/generator/generator.py
skytek_arcgis_integration/generator/jinja_extensions.py
skytek_arcgis_integration/generator/raster_layer_generator.py
skytek_arcgis_integration/generator/utils.py
skytek_arcgis_integration/management/__init__.py
skytek_arcgis_integration/management/commands/__init__.py
skytek_arcgis_integration/management/commands/generate_arcgis_integration.py
skytek_arcgis_integration-0.2.0.dist-info/LICENSE
skytek_arcgis_integration-0.2.0.dist-info/METADATA
skytek_arcgis_integration-0.2.0.dist-info/WHEEL
skytek_arcgis_integration-0.2.0.dist-info/top_level.txt
skytek_arcgis_integration-0.2.0.dist-info/RECORD
