Metadata-Version: 2.1
Name: skytek-arcgis-integration
Version: 0.2.0
Summary: skytek-arcgis-integration - expose ArcGIS data for Skytek's frontends
Home-page: http://github.com/Skytek/arcgis-integration
Author: Skytek Ltd.
Author-email: wiktor.latanowicz@skytek.com
License: LGPLv3
Classifier: Programming Language :: Python :: 3.9
Classifier: License :: OSI Approved :: GNU Lesser General Public License v3 (LGPLv3)
Classifier: Operating System :: OS Independent
Classifier: Topic :: Scientific/Engineering :: GIS
Requires-Python: >=3.9
License-File: LICENSE
Requires-Dist: skytek-generic-map-api >=0.4.0
Requires-Dist: cookiecutter >=2.1.0
